zjlang/__init__.py
zjlang/crypt.py
zjlang/datetime.py
zjlang/http.py
zjlang/logging.py
zjlang/number.py
zjlang/string.py
zjlang-0.0.1.dist-info/METADATA
zjlang-0.0.1.dist-info/RECORD
zjlang-0.0.1.dist-info/WHEEL
zjlang-0.0.1.dist-info/top_level.txt
