Metadata-Version: 2.1
Name: zjlang
Version: 0.0.1
Summary: base tools for python lang
Home-page: UNKNOWN
Author: tim.tang
Author-email: UNKNOWN
License: UNKNOWN
Platform: UNKNOWN
Classifier: Programming Language :: Python :: 3
